maxibot/__init__.py
maxibot/apihelper.py
maxibot/types.py
maxibot/util.py
maxibot/core/attachments/photo.py
maxibot/core/network/client.py
maxibot/core/network/polling.py
maxibot-1.0.7.dist-info/METADATA
maxibot-1.0.7.dist-info/WHEEL
maxibot-1.0.7.dist-info/top_level.txt
maxibot-1.0.7.dist-info/RECORD
