Metadata-Version: 2.4
Name: maxibot
Version: 1.0.7
Summary: Library for build bot in MAX
Project-URL: Homepage, https://github.com/mrProduktivnyy/maxibot
Project-URL: Documentation, https://github.com/mrProduktivnyy/maxibot/tree/main/maxibot/docs
Project-URL: Repository, https://github.com/mrProduktivnyy/maxibot
Project-URL: Issues, https://github.com/mrProduktivnyy/maxibot/issues
Keywords: max,bot,api,tools
Classifier: Development Status :: 5 - Production/Stable
Classifier: Programming Language :: Python :: 3
Classifier: Programming Language :: Python :: 3.8
Classifier: Programming Language :: Python :: 3.9
Classifier: Programming Language :: Python :: 3.10
Classifier: Programming Language :: Python :: 3.11
Classifier: Programming Language :: Python :: 3.12
Classifier: Environment :: Console
Classifier: License :: OSI Approved :: GNU General Public License v2 (GPLv2)
Requires-Python: >=3.8
Requires-Dist: requests==2.32.5
